{
  "students": [
    {
      "id": 1,
      "name": "Tri",
      "alterEgo": "Bruce Wayne"
    },
    {
      "id": 2,
      "name": "Thanh",
      "alterEgo": "Clark Kent"
    },
    {
      "id": 3,
      "name": "Thu",
      "alterEgo": "Princess Diana"
    },
    {
      "name": "Tri",
      "alterEgo": "Bruce Wayne test",
      "id": 4
    }
  ],
  "courses": [
    {
      "id": 1,
      "name": "maths",
      "coin": 500
    },
    {
      "id": 2,
      "name": "Physics",
      "coin": 400
    },
    {
      "id": 3,
      "name": "Chemistry",
      "coin": 200
    }
  ],
  "friends": [
    {
      "id": 1,
      "name": "Chandler Bing"
    },
    {
      "id": 2,
      "name": "Joey Tribbiani"
    },
    {
      "id": 3,
      "name": "Rachel Green"
    }
  ],
  "users": [
    {
      "id": "tri123456789@gmail.com",
      "student_id": 1,
      "course_ids": [
        1,
        2
      ]
    },
    {
      "id": "thanh123456789@gmail.com",
      "student_id": 2,
      "course_ids": [
        2,
        3
      ]
    },
    {
      "id": "thu123456789@gmail.com",
      "student_id": 3,
      "course_ids": [
        1,
        3
      ]
    }
  ],
  "colors": [
    {
      "id": 1,
      "label": "red"
    },
    {
      "id": 2,
      "label": "blue"
    },
    {
      "id": 3,
      "label": "green"
    },
    {
      "id": 4,
      "label": "deeppink"
    },
    {
      "id": 5,
      "label": "yellow"
    },
    {
      "id": 6,
      "label": "black"
    },
    {
      "id": 7,
      "label": "orange"
    },
    {
      "id": 8,
      "label": "cyan"
    },
    {
      "id": 9,
      "label": "purple"
    },
    {
      "id": 10,
      "label": "while"
    }
  ]
}